LICENSE
MANIFEST.in
NEWS
README
api.ini
config.yaml
git.config.yaml
httpserver.tac
packbackendserver.tac
packfrontendserver.tac
pygit2-requirements.txt
requirements.txt
setup.py
sshserver.tac
test-requirements.txt
virtserver.tac
static/global.css
static/launchpad-logo.png
static/launchpad.png
static/notification-private.png
static/private-banner.html
static/private.css
static/ubuntu-webfonts.css
turnip/__init__.py
turnip/config.py
turnip/helpers.py
turnip/log.py
turnip.egg-info/PKG-INFO
turnip.egg-info/SOURCES.txt
turnip.egg-info/dependency_links.txt
turnip.egg-info/entry_points.txt
turnip.egg-info/not-zip-safe
turnip.egg-info/paster_plugins.txt
turnip.egg-info/requires.txt
turnip.egg-info/top_level.txt
turnip/api/__init__.py
turnip/api/store.py
turnip/api/views.py
turnip/api/tests/__init__.py
turnip/api/tests/test_api.py
turnip/api/tests/test_helpers.py
turnip/api/tests/test_store.py
turnip/pack/__init__.py
turnip/pack/git.py
turnip/pack/helpers.py
turnip/pack/hookrpc.py
turnip/pack/http.py
turnip/pack/ssh.py
turnip/pack/hooks/__init__.py
turnip/pack/hooks/hook.py
turnip/pack/hooks/post-receive
turnip/pack/hooks/pre-receive
turnip/pack/tests/__init__.py
turnip/pack/tests/test_functional.py
turnip/pack/tests/test_git.py
turnip/pack/tests/test_helpers.py
turnip/pack/tests/test_hookrpc.py
turnip/pack/tests/test_hooks.py
turnip/pack/tests/test_http.py
turnip/pack/tests/data/ssh-host-key
turnip/pack/tests/data/ssh-host-key.pub
turnip/pack/tests/data/ssh-key
turnip/pack/tests/data/ssh-key.pub
turnip/tests/__init__.py
turnip/tests/test_helpers.py