Metadata-Version: 1.1
Name: turnip
Version: 0.1
Summary: turnip
Home-page: https://launchpad.net/turnip
Author: LAZR Developers
Author-email: lazr-developers@lists.launchpad.net
License: AGPL v3
Download-URL: https://launchpad.net/turnip/+download
Platform: UNKNOWN
Classifier: Development Status :: 4 - Beta
Classifier: Intended Audience :: Developers
Classifier: License :: OSI Approved :: GNU Affero General Public License v3
Classifier: Operating System :: OS Independent
Classifier: Programming Language :: Python
